pyprojector.cp37-win32.pyd
pyprojector-1.0.1.dist-info/LICENSE
pyprojector-1.0.1.dist-info/METADATA
pyprojector-1.0.1.dist-info/WHEEL
pyprojector-1.0.1.dist-info/top_level.txt
pyprojector-1.0.1.dist-info/RECORD
