Metadata-Version: 2.1
Name: pyprojector
Version: 1.0.1
Summary: pyprojector is an asyncronous window for rendering
Home-page: https://github.com/cprogrammer1994/pyprojector
Author: Szabolcs Dombi
Author-email: cprogrammer1994@gmail.com
License: MIT
Platform: UNKNOWN
